swapdog.py
swapdog-0.2.2.dist-info/METADATA
swapdog-0.2.2.dist-info/WHEEL
swapdog-0.2.2.dist-info/licenses/LICENSE
swapdog-0.2.2.dist-info/RECORD
