Metadata-Version: 2.4
Name: swapdog
Version: 0.2.2
Summary: Monitors RAM usage and enables swap devices
Project-URL: Repository, https://github.com/FLAK-ZOSO/SwapDog.git
Project-URL: Issues, https://github.com/FLAK-ZOSO/SwapDog/issues
Project-URL: Changelog, https://github.com/FLAK-ZOSO/SwapDog/blob/main/CHANGELOG.md
Author-email: FLAK-ZOSO <mattia.marchese.2006@gmail.com>
License: GNU General Public License v3.0 only
License-File: LICENSE
Keywords: daemon,memory,monitoring,ram,swap
Classifier: Development Status :: 3 - Alpha
Classifier: Intended Audience :: End Users/Desktop
Classifier: Intended Audience :: System Administrators
Classifier: License :: OSI Approved :: GNU General Public License v3 (GPLv3)
Classifier: Natural Language :: English
Classifier: Operating System :: MacOS
Classifier: Operating System :: POSIX
Classifier: Operating System :: Unix
Classifier: Programming Language :: Python :: 3
Classifier: Programming Language :: Python :: 3.9
Classifier: Programming Language :: Python :: 3.10
Classifier: Programming Language :: Python :: 3.11
Classifier: Programming Language :: Python :: 3.12
Classifier: Programming Language :: Python :: 3.13
Classifier: Programming Language :: Python :: Implementation :: CPython
Classifier: Topic :: System :: Monitoring
Classifier: Topic :: System :: Operating System
Classifier: Topic :: System :: Systems Administration
Classifier: Topic :: Utilities
Requires-Python: >=3.9
Requires-Dist: psutil
